[{"chat": 10, "turn": 2, "author": "Leolani", "utterance": "So your name is Caya?", "utterance_type": "STATEMENT", "position": "0-21", "subject": {"label": "your name", "type": []}, "predicate": {"label": "is", "type": []}, "object": {"label": "So Caya", "type": []}, "perspective": {}, "context_id": null, "date": "2022-02-19T01:09:39.482226", "place": "", "place_id": null, "country": "", "region": "", "city": "", "objects": [], "people": []}, {"chat": 10, "turn": 2, "author": "Leolani", "utterance": "So your name is Caya?", "utterance_type": "STATEMENT", "position": "0-21", "subject": {"label": "your name", "type": []}, "predicate": {"label": "is", "type": []}, "object": {"label": "Caya", "type": []}, "perspective": {}, "context_id": null, "date": "2022-02-19T01:09:39.482226", "place": "", "place_id": null, "country": "", "region": "", "city": "", "objects": [], "people": []}, {"chat": 10, "turn": 4, "author": "Leolani", "utterance": "Tell me anything, I love learning things", "utterance_type": "STATEMENT", "position": "0-40", "subject": {"label": "I", "type": []}, "predicate": {"label": "love", "type": []}, "object": {"label": "things", "type": []}, "perspective": {}, "context_id": null, "date": "2022-02-19T01:09:52.349287", "place": "", "place_id": null, "country": "", "region": "", "city": "", "objects": [], "people": []}, {"chat": 10, "turn": 4, "author": "Leolani", "utterance": "Tell me anything, I love learning things", "utterance_type": "STATEMENT", "position": "0-40", "subject": {"label": "I", "type": []}, "predicate": {"label": "love", "type": []}, "object": {"label": "learning things", "type": []}, "perspective": {}, "context_id": null, "date": "2022-02-19T01:09:52.349287", "place": "", "place_id": null, "country": "", "region": "", "city": "", "objects": [], "people": []}, {"chat": 10, "turn": 5, "author": "Leolani", "utterance": "A dog is an animal", "utterance_type": "STATEMENT", "position": "0-18", "subject": {"label": "dog", "type": []}, "predicate": {"label": "is", "type": []}, "object": {"label": "animal", "type": []}, "perspective": {}, "context_id": null, "date": "2022-02-19T01:09:58.877062", "place": "", "place_id": null, "country": "", "region": "", "city": "", "objects": [], "people": []}, {"chat": 10, "turn": 8, "author": "Leolani", "utterance": "you told me you like dogs", "utterance_type": "STATEMENT", "position": "0-25", "subject": {"label": "you", "type": []}, "predicate": {"label": "told", "type": []}, "object": {"label": "me", "type": []}, "perspective": {}, "context_id": null, "date": "2022-02-19T01:10:18.265837", "place": "", "place_id": null, "country": "", "region": "", "city": "", "objects": [], "people": []}, {"chat": 10, "turn": 8, "author": "Leolani", "utterance": "you told me you like dogs", "utterance_type": "STATEMENT", "position": "0-25", "subject": {"label": "you", "type": []}, "predicate": {"label": "told", "type": []}, "object": {"label": "you like dogs", "type": []}, "perspective": {}, "context_id": null, "date": "2022-02-19T01:10:18.265837", "place": "", "place_id": null, "country": "", "region": "", "city": "", "objects": [], "people": []}, {"chat": 10, "turn": 8, "author": "Leolani", "utterance": "you told me you like dogs", "utterance_type": "STATEMENT", "position": "0-25", "subject": {"label": "you", "type": []}, "predicate": {"label": "told", "type": []}, "object": {"label": "you", "type": []}, "perspective": {}, "context_id": null, "date": "2022-02-19T01:10:18.265837", "place": "", "place_id": null, "country": "", "region": "", "city": "", "objects": [], "people": []}, {"chat": 10, "turn": 11, "author": "Leolani", "utterance": "Apple pie smells good", "utterance_type": "STATEMENT", "position": "0-21", "subject": {"label": "Apple pie", "type": []}, "predicate": {"label": "smells", "type": []}, "object": {"label": "good", "type": []}, "perspective": {}, "context_id": null, "date": "2022-02-19T01:10:37.871551", "place": "", "place_id": null, "country": "", "region": "", "city": "", "objects": [], "people": []}, {"chat": 10, "turn": 12, "author": "Leolani", "utterance": "I am curious. What types of Instance like good do food orInstance usually smell", "utterance_type": "STATEMENT", "position": "0-79", "subject": {"label": "I", "type": []}, "predicate": {"label": "am", "type": []}, "object": {"label": "curious", "type": []}, "perspective": {}, "context_id": null, "date": "2022-02-19T01:10:44.294011", "place": "", "place_id": null, "country": "", "region": "", "city": "", "objects": [], "people": []}, {"chat": 10, "turn": 14, "author": "Leolani", "utterance": "Let me ask you something. What types of it orInstance like raining do Instance usually be", "utterance_type": "STATEMENT", "position": "0-89", "subject": {"label": "me", "type": []}, "predicate": {"label": "ask", "type": []}, "object": {"label": "you", "type": []}, "perspective": {}, "context_id": null, "date": "2022-02-19T01:10:57.291325", "place": "", "place_id": null, "country": "", "region": "", "city": "", "objects": [], "people": []}, {"chat": 10, "turn": 14, "author": "Leolani", "utterance": "Let me ask you something. What types of it orInstance like raining do Instance usually be", "utterance_type": "STATEMENT", "position": "0-89", "subject": {"label": "me", "type": []}, "predicate": {"label": "ask", "type": []}, "object": {"label": "something", "type": []}, "perspective": {}, "context_id": null, "date": "2022-02-19T01:10:57.291325", "place": "", "place_id": null, "country": "", "region": "", "city": "", "objects": [], "people": []}, {"chat": 10, "turn": 14, "author": "Leolani", "utterance": "Let me ask you something. What types of it orInstance like raining do Instance usually be", "utterance_type": "STATEMENT", "position": "0-89", "subject": {"label": "Instance", "type": []}, "predicate": {"label": "usually be like", "type": []}, "object": {"label": "raining", "type": []}, "perspective": {}, "context_id": null, "date": "2022-02-19T01:10:57.291325", "place": "", "place_id": null, "country": "", "region": "", "city": "", "objects": [], "people": []}, {"chat": 10, "turn": 14, "author": "Leolani", "utterance": "Let me ask you something. What types of it orInstance like raining do Instance usually be", "utterance_type": "STATEMENT", "position": "0-89", "subject": {"label": "Instance", "type": []}, "predicate": {"label": "be like", "type": []}, "object": {"label": "raining", "type": []}, "perspective": {}, "context_id": null, "date": "2022-02-19T01:10:57.291325", "place": "", "place_id": null, "country": "", "region": "", "city": "", "objects": [], "people": []}, {"chat": 10, "turn": 16, "author": "Leolani", "utterance": "May I ask you why?", "utterance_type": "STATEMENT", "position": "0-18", "subject": {"label": "I", "type": []}, "predicate": {"label": "May ask", "type": []}, "object": {"label": "you", "type": []}, "perspective": {}, "context_id": null, "date": "2022-02-19T01:11:10.373603", "place": "", "place_id": null, "country": "", "region": "", "city": "", "objects": [], "people": []}, {"chat": 10, "turn": 17, "author": "Leolani", "utterance": "Lions are territorial animals", "utterance_type": "STATEMENT", "position": "0-29", "subject": {"label": "Lions", "type": []}, "predicate": {"label": "are", "type": []}, "object": {"label": "animals", "type": []}, "perspective": {}, "context_id": null, "date": "2022-02-19T01:11:16.870296", "place": "", "place_id": null, "country": "", "region": "", "city": "", "objects": [], "people": []}, {"chat": 10, "turn": 17, "author": "Leolani", "utterance": "Lions are territorial animals", "utterance_type": "STATEMENT", "position": "0-29", "subject": {"label": "Lions", "type": []}, "predicate": {"label": "are", "type": []}, "object": {"label": "territorial animals", "type": []}, "perspective": {}, "context_id": null, "date": "2022-02-19T01:11:16.870296", "place": "", "place_id": null, "country": "", "region": "", "city": "", "objects": [], "people": []}, {"chat": 10, "turn": 19, "author": "Leolani", "utterance": "Ella likes books", "utterance_type": "STATEMENT", "position": "0-16", "subject": {"label": "Ella", "type": []}, "predicate": {"label": "likes", "type": []}, "object": {"label": "books", "type": []}, "perspective": {}, "context_id": null, "date": "2022-02-19T01:11:29.771923", "place": "", "place_id": null, "country": "", "region": "", "city": "", "objects": [], "people": []}, {"chat": 10, "turn": 20, "author": "Leolani", "utterance": "I am curious. Has ella own object?", "utterance_type": "STATEMENT", "position": "0-34", "subject": {"label": "I", "type": []}, "predicate": {"label": "am", "type": []}, "object": {"label": "curious", "type": []}, "perspective": {}, "context_id": null, "date": "2022-02-19T01:11:36.233698", "place": "", "place_id": null, "country": "", "region": "", "city": "", "objects": [], "people": []}, {"chat": 10, "turn": 21, "author": "Leolani", "utterance": "Ella is a person", "utterance_type": "STATEMENT", "position": "0-16", "subject": {"label": "Ella", "type": []}, "predicate": {"label": "is", "type": []}, "object": {"label": "person", "type": []}, "perspective": {}, "context_id": null, "date": "2022-02-19T01:11:42.769507", "place": "", "place_id": null, "country": "", "region": "", "city": "", "objects": [], "people": []}, {"chat": 10, "turn": 24, "author": "Leolani", "utterance": "I just learned something, I am excited to get to know about you!", "utterance_type": "STATEMENT", "position": "0-64", "subject": {"label": "I", "type": []}, "predicate": {"label": "just learned", "type": []}, "object": {"label": "something", "type": []}, "perspective": {}, "context_id": null, "date": "2022-02-19T01:12:02.355673", "place": "", "place_id": null, "country": "", "region": "", "city": "", "objects": [], "people": []}, {"chat": 10, "turn": 24, "author": "Leolani", "utterance": "I just learned something, I am excited to get to know about you!", "utterance_type": "STATEMENT", "position": "0-64", "subject": {"label": "I", "type": []}, "predicate": {"label": "get", "type": []}, "object": {"label": "know", "type": []}, "perspective": {}, "context_id": null, "date": "2022-02-19T01:12:02.355673", "place": "", "place_id": null, "country": "", "region": "", "city": "", "objects": [], "people": []}, {"chat": 10, "turn": 24, "author": "Leolani", "utterance": "I just learned something, I am excited to get to know about you!", "utterance_type": "STATEMENT", "position": "0-64", "subject": {"label": "I", "type": []}, "predicate": {"label": "am", "type": []}, "object": {"label": "excited", "type": []}, "perspective": {}, "context_id": null, "date": "2022-02-19T01:12:02.355673", "place": "", "place_id": null, "country": "", "region": "", "city": "", "objects": [], "people": []}, {"chat": 10, "turn": 24, "author": "Leolani", "utterance": "I just learned something, I am excited to get to know about you!", "utterance_type": "STATEMENT", "position": "0-64", "subject": {"label": "I", "type": []}, "predicate": {"label": "learned", "type": []}, "object": {"label": "something", "type": []}, "perspective": {}, "context_id": null, "date": "2022-02-19T01:12:02.355673", "place": "", "place_id": null, "country": "", "region": "", "city": "", "objects": [], "people": []}, {"chat": 10, "turn": 24, "author": "Leolani", "utterance": "I just learned something, I am excited to get to know about you!", "utterance_type": "STATEMENT", "position": "0-64", "subject": {"label": "I", "type": []}, "predicate": {"label": "get", "type": []}, "object": {"label": "to know about you", "type": []}, "perspective": {}, "context_id": null, "date": "2022-02-19T01:12:02.355673", "place": "", "place_id": null, "country": "", "region": "", "city": "", "objects": [], "people": []}, {"chat": 10, "turn": 24, "author": "Leolani", "utterance": "I just learned something, I am excited to get to know about you!", "utterance_type": "STATEMENT", "position": "0-64", "subject": {"label": "I", "type": []}, "predicate": {"label": "get", "type": []}, "object": {"label": "know about you", "type": []}, "perspective": {}, "context_id": null, "date": "2022-02-19T01:12:02.355673", "place": "", "place_id": null, "country": "", "region": "", "city": "", "objects": [], "people": []}, {"chat": 10, "turn": 24, "author": "Leolani", "utterance": "I just learned something, I am excited to get to know about you!", "utterance_type": "STATEMENT", "position": "0-64", "subject": {"label": "I", "type": []}, "predicate": {"label": "get", "type": []}, "object": {"label": "to know", "type": []}, "perspective": {}, "context_id": null, "date": "2022-02-19T01:12:02.355673", "place": "", "place_id": null, "country": "", "region": "", "city": "", "objects": [], "people": []}, {"chat": 10, "turn": 26, "author": "Leolani", "utterance": "you told me you own no object and that you own a laptop ", "utterance_type": "STATEMENT", "position": "0-56", "subject": {"label": "you", "type": []}, "predicate": {"label": "told", "type": []}, "object": {"label": "me", "type": []}, "perspective": {}, "context_id": null, "date": "2022-02-19T01:12:15.412389", "place": "", "place_id": null, "country": "", "region": "", "city": "", "objects": [], "people": []}, {"chat": 10, "turn": 27, "author": "Leolani", "utterance": "A laptop is a object", "utterance_type": "STATEMENT", "position": "0-20", "subject": {"label": "laptop", "type": []}, "predicate": {"label": "is", "type": []}, "object": {"label": "object", "type": []}, "perspective": {}, "context_id": null, "date": "2022-02-19T01:12:21.918122", "place": "", "place_id": null, "country": "", "region": "", "city": "", "objects": [], "people": []}, {"chat": 10, "turn": 29, "author": "Leolani", "utterance": "Mincke is 24 years old", "utterance_type": "STATEMENT", "position": "0-22", "subject": {"label": "Mincke", "type": []}, "predicate": {"label": "is old", "type": []}, "object": {"label": "24 years", "type": []}, "perspective": {}, "context_id": null, "date": "2022-02-19T01:12:34.902711", "place": "", "place_id": null, "country": "", "region": "", "city": "", "objects": [], "people": []}, {"chat": 10, "turn": 30, "author": "Leolani", "utterance": "I am glad to have learned something new. I did not know anybody that mincke be", "utterance_type": "STATEMENT", "position": "0-78", "subject": {"label": "I", "type": []}, "predicate": {"label": "learned", "type": []}, "object": {"label": "something new", "type": []}, "perspective": {}, "context_id": null, "date": "2022-02-19T01:12:41.367177", "place": "", "place_id": null, "country": "", "region": "", "city": "", "objects": [], "people": []}, {"chat": 10, "turn": 30, "author": "Leolani", "utterance": "I am glad to have learned something new. I did not know anybody that mincke be", "utterance_type": "STATEMENT", "position": "0-78", "subject": {"label": "I", "type": []}, "predicate": {"label": "am", "type": []}, "object": {"label": "glad", "type": []}, "perspective": {}, "context_id": null, "date": "2022-02-19T01:12:41.367177", "place": "", "place_id": null, "country": "", "region": "", "city": "", "objects": [], "people": []}, {"chat": 10, "turn": 30, "author": "Leolani", "utterance": "I am glad to have learned something new. I did not know anybody that mincke be", "utterance_type": "STATEMENT", "position": "0-78", "subject": {"label": "I", "type": []}, "predicate": {"label": "learned", "type": []}, "object": {"label": "something", "type": []}, "perspective": {}, "context_id": null, "date": "2022-02-19T01:12:41.367177", "place": "", "place_id": null, "country": "", "region": "", "city": "", "objects": [], "people": []}, {"chat": 10, "turn": 31, "author": "Leolani", "utterance": "I am 2 years younger than Mincke", "utterance_type": "STATEMENT", "position": "0-32", "subject": {"label": "I", "type": []}, "predicate": {"label": "am younger", "type": []}, "object": {"label": "2 years", "type": []}, "perspective": {}, "context_id": null, "date": "2022-02-19T01:12:47.880011", "place": "", "place_id": null, "country": "", "region": "", "city": "", "objects": [], "people": []}, {"chat": 10, "turn": 31, "author": "Leolani", "utterance": "I am 2 years younger than Mincke", "utterance_type": "STATEMENT", "position": "0-32", "subject": {"label": "I", "type": []}, "predicate": {"label": "am", "type": []}, "object": {"label": "2 years younger than Mincke", "type": []}, "perspective": {}, "context_id": null, "date": "2022-02-19T01:12:47.880011", "place": "", "place_id": null, "country": "", "region": "", "city": "", "objects": [], "people": []}, {"chat": 10, "turn": 32, "author": "Leolani", "utterance": "I am curious. Has caya experience smell?", "utterance_type": "STATEMENT", "position": "0-40", "subject": {"label": "I", "type": []}, "predicate": {"label": "am", "type": []}, "object": {"label": "curious", "type": []}, "perspective": {}, "context_id": null, "date": "2022-02-19T01:12:54.384674", "place": "", "place_id": null, "country": "", "region": "", "city": "", "objects": [], "people": []}, {"chat": 10, "turn": 34, "author": "Leolani", "utterance": "Let me ask you something. What types can all people can smell", "utterance_type": "STATEMENT", "position": "0-61", "subject": {"label": "me", "type": []}, "predicate": {"label": "ask", "type": []}, "object": {"label": "you", "type": []}, "perspective": {}, "context_id": null, "date": "2022-02-19T01:13:07.372304", "place": "", "place_id": null, "country": "", "region": "", "city": "", "objects": [], "people": []}, {"chat": 10, "turn": 34, "author": "Leolani", "utterance": "Let me ask you something. What types can all people can smell", "utterance_type": "STATEMENT", "position": "0-61", "subject": {"label": "me", "type": []}, "predicate": {"label": "ask", "type": []}, "object": {"label": "something", "type": []}, "perspective": {}, "context_id": null, "date": "2022-02-19T01:13:07.372304", "place": "", "place_id": null, "country": "", "region": "", "city": "", "objects": [], "people": []}, {"chat": 10, "turn": 41, "author": "Leolani", "utterance": "Mincke likes Apple pie", "utterance_type": "STATEMENT", "position": "0-22", "subject": {"label": "Mincke", "type": []}, "predicate": {"label": "likes", "type": []}, "object": {"label": "Apple pie", "type": []}, "perspective": {}, "context_id": null, "date": "2022-02-19T01:13:52.971632", "place": "", "place_id": null, "country": "", "region": "", "city": "", "objects": [], "people": []}, {"chat": 10, "turn": 42, "author": "Leolani", "utterance": "I just learned something, I had never heard about apple pie before!", "utterance_type": "STATEMENT", "position": "0-67", "subject": {"label": "I", "type": []}, "predicate": {"label": "had heard about", "type": []}, "object": {"label": "apple pie", "type": []}, "perspective": {}, "context_id": null, "date": "2022-02-19T01:13:59.356761", "place": "", "place_id": null, "country": "", "region": "", "city": "", "objects": [], "people": []}, {"chat": 10, "turn": 42, "author": "Leolani", "utterance": "I just learned something, I had never heard about apple pie before!", "utterance_type": "STATEMENT", "position": "0-67", "subject": {"label": "I", "type": []}, "predicate": {"label": "just learned", "type": []}, "object": {"label": "something", "type": []}, "perspective": {}, "context_id": null, "date": "2022-02-19T01:13:59.356761", "place": "", "place_id": null, "country": "", "region": "", "city": "", "objects": [], "people": []}, {"chat": 10, "turn": 42, "author": "Leolani", "utterance": "I just learned something, I had never heard about apple pie before!", "utterance_type": "STATEMENT", "position": "0-67", "subject": {"label": "I", "type": []}, "predicate": {"label": "learned", "type": []}, "object": {"label": "something", "type": []}, "perspective": {}, "context_id": null, "date": "2022-02-19T01:13:59.356761", "place": "", "place_id": null, "country": "", "region": "", "city": "", "objects": [], "people": []}, {"chat": 10, "turn": 42, "author": "Leolani", "utterance": "I just learned something, I had never heard about apple pie before!", "utterance_type": "STATEMENT", "position": "0-67", "subject": {"label": "I", "type": []}, "predicate": {"label": "had heard before about", "type": []}, "object": {"label": "apple pie", "type": []}, "perspective": {}, "context_id": null, "date": "2022-02-19T01:13:59.356761", "place": "", "place_id": null, "country": "", "region": "", "city": "", "objects": [], "people": []}, {"chat": 10, "turn": 43, "author": "Leolani", "utterance": "Apple pie is a cake ", "utterance_type": "STATEMENT", "position": "0-20", "subject": {"label": "Apple pie", "type": []}, "predicate": {"label": "is", "type": []}, "object": {"label": "cake", "type": []}, "perspective": {}, "context_id": null, "date": "2022-02-19T01:14:05.858268", "place": "", "place_id": null, "country": "", "region": "", "city": "", "objects": [], "people": []}, {"chat": 10, "turn": 45, "author": "Leolani", "utterance": "A cake is a dish", "utterance_type": "STATEMENT", "position": "0-16", "subject": {"label": "cake", "type": []}, "predicate": {"label": "is", "type": []}, "object": {"label": "dish", "type": []}, "perspective": {}, "context_id": null, "date": "2022-02-19T01:14:20.498163", "place": "", "place_id": null, "country": "", "region": "", "city": "", "objects": [], "people": []}, {"chat": 10, "turn": 47, "author": "Leolani", "utterance": "I like pizza", "utterance_type": "STATEMENT", "position": "0-12", "subject": {"label": "I", "type": []}, "predicate": {"label": "like", "type": []}, "object": {"label": "pizza", "type": []}, "perspective": {}, "context_id": null, "date": "2022-02-19T01:14:35.294593", "place": "", "place_id": null, "country": "", "region": "", "city": "", "objects": [], "people": []}, {"chat": 10, "turn": 48, "author": "Leolani", "utterance": "I am curious. Has caya favorite interest?", "utterance_type": "STATEMENT", "position": "0-41", "subject": {"label": "I", "type": []}, "predicate": {"label": "am", "type": []}, "object": {"label": "curious", "type": []}, "perspective": {}, "context_id": null, "date": "2022-02-19T01:14:42.083366", "place": "", "place_id": null, "country": "", "region": "", "city": "", "objects": [], "people": []}, {"chat": 10, "turn": 49, "author": "Leolani", "utterance": "I am an equestrian", "utterance_type": "STATEMENT", "position": "0-18", "subject": {"label": "I", "type": []}, "predicate": {"label": "am", "type": []}, "object": {"label": "equestrian", "type": []}, "perspective": {}, "context_id": null, "date": "2022-02-19T01:14:49.720279", "place": "", "place_id": null, "country": "", "region": "", "city": "", "objects": [], "people": []}, {"chat": 10, "turn": 50, "author": "Leolani", "utterance": "Cool! Now I know 2 items that caya be, like 2 years younger than mincke and 2 years younger than mincke", "utterance_type": "STATEMENT", "position": "0-103", "subject": {"label": "caya", "type": []}, "predicate": {"label": "be younger", "type": []}, "object": {"label": "2 years", "type": []}, "perspective": {}, "context_id": null, "date": "2022-02-19T01:14:56.151336", "place": "", "place_id": null, "country": "", "region": "", "city": "", "objects": [], "people": []}, {"chat": 10, "turn": 50, "author": "Leolani", "utterance": "Cool! Now I know 2 items that caya be, like 2 years younger than mincke and 2 years younger than mincke", "utterance_type": "STATEMENT", "position": "0-103", "subject": {"label": "caya", "type": []}, "predicate": {"label": "be", "type": []}, "object": {"label": "2 years younger than mincke than mincke", "type": []}, "perspective": {}, "context_id": null, "date": "2022-02-19T01:14:56.151336", "place": "", "place_id": null, "country": "", "region": "", "city": "", "objects": [], "people": []}, {"chat": 10, "turn": 50, "author": "Leolani", "utterance": "Cool! Now I know 2 items that caya be, like 2 years younger than mincke and 2 years younger than mincke", "utterance_type": "STATEMENT", "position": "0-103", "subject": {"label": "caya", "type": []}, "predicate": {"label": "be", "type": []}, "object": {"label": "2 years younger than mincke", "type": []}, "perspective": {}, "context_id": null, "date": "2022-02-19T01:14:56.151336", "place": "", "place_id": null, "country": "", "region": "", "city": "", "objects": [], "people": []}, {"chat": 10, "turn": 50, "author": "Leolani", "utterance": "Cool! Now I know 2 items that caya be, like 2 years younger than mincke and 2 years younger than mincke", "utterance_type": "STATEMENT", "position": "0-103", "subject": {"label": "I", "type": []}, "predicate": {"label": "Now know", "type": []}, "object": {"label": "2 items", "type": []}, "perspective": {}, "context_id": null, "date": "2022-02-19T01:14:56.151336", "place": "", "place_id": null, "country": "", "region": "", "city": "", "objects": [], "people": []}, {"chat": 10, "turn": 50, "author": "Leolani", "utterance": "Cool! Now I know 2 items that caya be, like 2 years younger than mincke and 2 years younger than mincke", "utterance_type": "STATEMENT", "position": "0-103", "subject": {"label": "I", "type": []}, "predicate": {"label": "know", "type": []}, "object": {"label": "2 items", "type": []}, "perspective": {}, "context_id": null, "date": "2022-02-19T01:14:56.151336", "place": "", "place_id": null, "country": "", "region": "", "city": "", "objects": [], "people": []}, {"chat": 10, "turn": 51, "author": "Leolani", "utterance": "Mincke lives in Utrecht", "utterance_type": "STATEMENT", "position": "0-23", "subject": {"label": "Mincke", "type": []}, "predicate": {"label": "lives in", "type": []}, "object": {"label": "Utrecht", "type": []}, "perspective": {}, "context_id": null, "date": "2022-02-19T01:15:02.763527", "place": "", "place_id": null, "country": "", "region": "", "city": "", "objects": [], "people": []}, {"chat": 10, "turn": 52, "author": "Leolani", "utterance": "I just learned something, I had never heard about mincke before!", "utterance_type": "STATEMENT", "position": "0-64", "subject": {"label": "I", "type": []}, "predicate": {"label": "had heard before about", "type": []}, "object": {"label": "mincke", "type": []}, "perspective": {}, "context_id": null, "date": "2022-02-19T01:15:09.224757", "place": "", "place_id": null, "country": "", "region": "", "city": "", "objects": [], "people": []}, {"chat": 10, "turn": 52, "author": "Leolani", "utterance": "I just learned something, I had never heard about mincke before!", "utterance_type": "STATEMENT", "position": "0-64", "subject": {"label": "I", "type": []}, "predicate": {"label": "just learned", "type": []}, "object": {"label": "something", "type": []}, "perspective": {}, "context_id": null, "date": "2022-02-19T01:15:09.224757", "place": "", "place_id": null, "country": "", "region": "", "city": "", "objects": [], "people": []}, {"chat": 10, "turn": 52, "author": "Leolani", "utterance": "I just learned something, I had never heard about mincke before!", "utterance_type": "STATEMENT", "position": "0-64", "subject": {"label": "I", "type": []}, "predicate": {"label": "had heard about", "type": []}, "object": {"label": "mincke", "type": []}, "perspective": {}, "context_id": null, "date": "2022-02-19T01:15:09.224757", "place": "", "place_id": null, "country": "", "region": "", "city": "", "objects": [], "people": []}, {"chat": 10, "turn": 52, "author": "Leolani", "utterance": "I just learned something, I had never heard about mincke before!", "utterance_type": "STATEMENT", "position": "0-64", "subject": {"label": "I", "type": []}, "predicate": {"label": "learned", "type": []}, "object": {"label": "something", "type": []}, "perspective": {}, "context_id": null, "date": "2022-02-19T01:15:09.224757", "place": "", "place_id": null, "country": "", "region": "", "city": "", "objects": [], "people": []}, {"chat": 10, "turn": 54, "author": "Leolani", "utterance": "you told me mincke is 24 years old", "utterance_type": "STATEMENT", "position": "0-34", "subject": {"label": "you", "type": []}, "predicate": {"label": "told", "type": []}, "object": {"label": "me", "type": []}, "perspective": {}, "context_id": null, "date": "2022-02-19T01:15:22.197635", "place": "", "place_id": null, "country": "", "region": "", "city": "", "objects": [], "people": []}, {"chat": 10, "turn": 54, "author": "Leolani", "utterance": "you told me mincke is 24 years old", "utterance_type": "STATEMENT", "position": "0-34", "subject": {"label": "you", "type": []}, "predicate": {"label": "told", "type": []}, "object": {"label": "mincke", "type": []}, "perspective": {}, "context_id": null, "date": "2022-02-19T01:15:22.197635", "place": "", "place_id": null, "country": "", "region": "", "city": "", "objects": [], "people": []}, {"chat": 10, "turn": 55, "author": "Leolani", "utterance": "Mincke is my friend", "utterance_type": "STATEMENT", "position": "0-19", "subject": {"label": "Mincke", "type": []}, "predicate": {"label": "is", "type": []}, "object": {"label": "my friend", "type": []}, "perspective": {}, "context_id": null, "date": "2022-02-19T01:15:28.600167", "place": "", "place_id": null, "country": "", "region": "", "city": "", "objects": [], "people": []}, {"chat": 10, "turn": 56, "author": "Leolani", "utterance": "I would like to know. Has caya friend dislike by a agent?", "utterance_type": "STATEMENT", "position": "0-57", "subject": {"label": "I", "type": []}, "predicate": {"label": "would like", "type": []}, "object": {"label": "know", "type": []}, "perspective": {}, "context_id": null, "date": "2022-02-19T01:15:35.106646", "place": "", "place_id": null, "country": "", "region": "", "city": "", "objects": [], "people": []}, {"chat": 10, "turn": 56, "author": "Leolani", "utterance": "I would like to know. Has caya friend dislike by a agent?", "utterance_type": "STATEMENT", "position": "0-57", "subject": {"label": "I", "type": []}, "predicate": {"label": "would like", "type": []}, "object": {"label": "to know", "type": []}, "perspective": {}, "context_id": null, "date": "2022-02-19T01:15:35.106646", "place": "", "place_id": null, "country": "", "region": "", "city": "", "objects": [], "people": []}, {"chat": 10, "turn": 58, "author": "Leolani", "utterance": "So let it be written, ... so let it be done", "utterance_type": "STATEMENT", "position": "0-43", "subject": {"label": "it", "type": []}, "predicate": {"label": "be", "type": []}, "object": {"label": "written", "type": []}, "perspective": {}, "context_id": null, "date": "2022-02-19T01:15:47.991437", "place": "", "place_id": null, "country": "", "region": "", "city": "", "objects": [], "people": []}, {"chat": 10, "turn": 58, "author": "Leolani", "utterance": "So let it be written, ... so let it be done", "utterance_type": "STATEMENT", "position": "0-43", "subject": {"label": "it", "type": []}, "predicate": {"label": "be", "type": []}, "object": {"label": "done", "type": []}, "perspective": {}, "context_id": null, "date": "2022-02-19T01:15:47.991437", "place": "", "place_id": null, "country": "", "region": "", "city": "", "objects": [], "people": []}, {"chat": 10, "turn": 59, "author": "Leolani", "utterance": "Hey! I would like to know your name! Mincke?", "utterance_type": "STATEMENT", "position": "0-44", "subject": {"label": "I", "type": []}, "predicate": {"label": "would like", "type": []}, "object": {"label": "know", "type": []}, "perspective": {}, "context_id": null, "date": "2022-02-19T01:15:54.549848", "place": "", "place_id": null, "country": "", "region": "", "city": "", "objects": [], "people": []}, {"chat": 10, "turn": 59, "author": "Leolani", "utterance": "Hey! I would like to know your name! Mincke?", "utterance_type": "STATEMENT", "position": "0-44", "subject": {"label": "I", "type": []}, "predicate": {"label": "would like", "type": []}, "object": {"label": "to know", "type": []}, "perspective": {}, "context_id": null, "date": "2022-02-19T01:15:54.549848", "place": "", "place_id": null, "country": "", "region": "", "city": "", "objects": [], "people": []}, {"chat": 10, "turn": 59, "author": "Leolani", "utterance": "Hey! I would like to know your name! Mincke?", "utterance_type": "STATEMENT", "position": "0-44", "subject": {"label": "I", "type": []}, "predicate": {"label": "know", "type": []}, "object": {"label": "your name", "type": []}, "perspective": {}, "context_id": null, "date": "2022-02-19T01:15:54.549848", "place": "", "place_id": null, "country": "", "region": "", "city": "", "objects": [], "people": []}, {"chat": 10, "turn": 61, "author": "Leolani", "utterance": "So your name is Mincke?", "utterance_type": "STATEMENT", "position": "0-23", "subject": {"label": "your name", "type": []}, "predicate": {"label": "is", "type": []}, "object": {"label": "Mincke", "type": []}, "perspective": {}, "context_id": null, "date": "2022-02-19T01:16:07.559477", "place": "", "place_id": null, "country": "", "region": "", "city": "", "objects": [], "people": []}, {"chat": 10, "turn": 61, "author": "Leolani", "utterance": "So your name is Mincke?", "utterance_type": "STATEMENT", "position": "0-23", "subject": {"label": "your name", "type": []}, "predicate": {"label": "is", "type": []}, "object": {"label": "So Mincke", "type": []}, "perspective": {}, "context_id": null, "date": "2022-02-19T01:16:07.559477", "place": "", "place_id": null, "country": "", "region": "", "city": "", "objects": [], "people": []}, {"chat": 10, "turn": 63, "author": "Leolani", "utterance": "Tell me anything, I love learning things", "utterance_type": "STATEMENT", "position": "0-40", "subject": {"label": "I", "type": []}, "predicate": {"label": "love", "type": []}, "object": {"label": "things", "type": []}, "perspective": {}, "context_id": null, "date": "2022-02-19T01:16:20.457005", "place": "", "place_id": null, "country": "", "region": "", "city": "", "objects": [], "people": []}, {"chat": 10, "turn": 63, "author": "Leolani", "utterance": "Tell me anything, I love learning things", "utterance_type": "STATEMENT", "position": "0-40", "subject": {"label": "I", "type": []}, "predicate": {"label": "love", "type": []}, "object": {"label": "learning things", "type": []}, "perspective": {}, "context_id": null, "date": "2022-02-19T01:16:20.457005", "place": "", "place_id": null, "country": "", "region": "", "city": "", "objects": [], "people": []}, {"chat": 10, "turn": 65, "author": "Leolani", "utterance": "Let me ask you something. Has mincke like by agent?", "utterance_type": "STATEMENT", "position": "0-51", "subject": {"label": "me", "type": []}, "predicate": {"label": "ask", "type": []}, "object": {"label": "you", "type": []}, "perspective": {}, "context_id": null, "date": "2022-02-19T01:16:33.386263", "place": "", "place_id": null, "country": "", "region": "", "city": "", "objects": [], "people": []}, {"chat": 10, "turn": 65, "author": "Leolani", "utterance": "Let me ask you something. Has mincke like by agent?", "utterance_type": "STATEMENT", "position": "0-51", "subject": {"label": "me", "type": []}, "predicate": {"label": "ask", "type": []}, "object": {"label": "something", "type": []}, "perspective": {}, "context_id": null, "date": "2022-02-19T01:16:33.386263", "place": "", "place_id": null, "country": "", "region": "", "city": "", "objects": [], "people": []}, {"chat": 10, "turn": 68, "author": "Leolani", "utterance": "Yesterday the weather was sunny", "utterance_type": "STATEMENT", "position": "0-31", "subject": {"label": "weather", "type": []}, "predicate": {"label": "was sunny at_time", "type": []}, "object": {"label": "Yesterday", "type": []}, "perspective": {}, "context_id": null, "date": "2022-02-19T01:16:52.654872", "place": "", "place_id": null, "country": "", "region": "", "city": "", "objects": [], "people": []}, {"chat": 10, "turn": 69, "author": "Leolani", "utterance": "I just learned something, I had never heard about sunny before!", "utterance_type": "STATEMENT", "position": "0-63", "subject": {"label": "I", "type": []}, "predicate": {"label": "had heard about", "type": []}, "object": {"label": "sunny", "type": []}, "perspective": {}, "context_id": null, "date": "2022-02-19T01:16:59.102379", "place": "", "place_id": null, "country": "", "region": "", "city": "", "objects": [], "people": []}, {"chat": 10, "turn": 69, "author": "Leolani", "utterance": "I just learned something, I had never heard about sunny before!", "utterance_type": "STATEMENT", "position": "0-63", "subject": {"label": "I", "type": []}, "predicate": {"label": "had heard before about", "type": []}, "object": {"label": "sunny", "type": []}, "perspective": {}, "context_id": null, "date": "2022-02-19T01:16:59.102379", "place": "", "place_id": null, "country": "", "region": "", "city": "", "objects": [], "people": []}, {"chat": 10, "turn": 69, "author": "Leolani", "utterance": "I just learned something, I had never heard about sunny before!", "utterance_type": "STATEMENT", "position": "0-63", "subject": {"label": "I", "type": []}, "predicate": {"label": "just learned", "type": []}, "object": {"label": "something", "type": []}, "perspective": {}, "context_id": null, "date": "2022-02-19T01:16:59.102379", "place": "", "place_id": null, "country": "", "region": "", "city": "", "objects": [], "people": []}, {"chat": 10, "turn": 69, "author": "Leolani", "utterance": "I just learned something, I had never heard about sunny before!", "utterance_type": "STATEMENT", "position": "0-63", "subject": {"label": "I", "type": []}, "predicate": {"label": "learned", "type": []}, "object": {"label": "something", "type": []}, "perspective": {}, "context_id": null, "date": "2022-02-19T01:16:59.102379", "place": "", "place_id": null, "country": "", "region": "", "city": "", "objects": [], "people": []}, {"chat": 10, "turn": 72, "author": "Leolani", "utterance": "Do you know Caya", "utterance_type": "STATEMENT", "position": "0-16", "subject": {"label": "you", "type": []}, "predicate": {"label": "Do know", "type": []}, "object": {"label": "Caya", "type": []}, "perspective": {}, "context_id": null, "date": "2022-02-19T01:17:18.464015", "place": "", "place_id": null, "country": "", "region": "", "city": "", "objects": [], "people": []}, {"chat": 10, "turn": 73, "author": "Leolani", "utterance": "I know agent usually do know person, but I do not know this case", "utterance_type": "STATEMENT", "position": "0-64", "subject": {"label": "agent", "type": []}, "predicate": {"label": "know", "type": []}, "object": {"label": "person", "type": []}, "perspective": {}, "context_id": null, "date": "2022-02-19T01:17:24.932820", "place": "", "place_id": null, "country": "", "region": "", "city": "", "objects": [], "people": []}, {"chat": 10, "turn": 73, "author": "Leolani", "utterance": "I know agent usually do know person, but I do not know this case", "utterance_type": "STATEMENT", "position": "0-64", "subject": {"label": "agent", "type": []}, "predicate": {"label": "usually know", "type": []}, "object": {"label": "person", "type": []}, "perspective": {}, "context_id": null, "date": "2022-02-19T01:17:24.932820", "place": "", "place_id": null, "country": "", "region": "", "city": "", "objects": [], "people": []}, {"chat": 10, "turn": 74, "author": "Leolani", "utterance": "Is Caya your friend? ", "utterance_type": "STATEMENT", "position": "0-21", "subject": {"label": "Caya", "type": []}, "predicate": {"label": "Is", "type": []}, "object": {"label": "your friend", "type": []}, "perspective": {}, "context_id": null, "date": "2022-02-19T01:17:31.479013", "place": "", "place_id": null, "country": "", "region": "", "city": "", "objects": [], "people": []}, {"chat": 10, "turn": 75, "author": "Leolani", "utterance": "I know agent usually is agent, but I do not know this case", "utterance_type": "STATEMENT", "position": "0-58", "subject": {"label": "agent", "type": []}, "predicate": {"label": "is", "type": []}, "object": {"label": "agent", "type": []}, "perspective": {}, "context_id": null, "date": "2022-02-19T01:17:37.930335", "place": "", "place_id": null, "country": "", "region": "", "city": "", "objects": [], "people": []}, {"chat": 10, "turn": 75, "author": "Leolani", "utterance": "I know agent usually is agent, but I do not know this case", "utterance_type": "STATEMENT", "position": "0-58", "subject": {"label": "agent", "type": []}, "predicate": {"label": "is", "type": []}, "object": {"label": "usually agent", "type": []}, "perspective": {}, "context_id": null, "date": "2022-02-19T01:17:37.930335", "place": "", "place_id": null, "country": "", "region": "", "city": "", "objects": [], "people": []}, {"chat": 10, "turn": 78, "author": "Leolani", "utterance": "I live in Utrecht", "utterance_type": "STATEMENT", "position": "0-17", "subject": {"label": "I", "type": []}, "predicate": {"label": "live in", "type": []}, "object": {"label": "Utrecht", "type": []}, "perspective": {}, "context_id": null, "date": "2022-02-19T01:17:57.483913", "place": "", "place_id": null, "country": "", "region": "", "city": "", "objects": [], "people": []}, {"chat": 10, "turn": 79, "author": "Leolani", "utterance": "I did not know that! I had never heard about utrecht before!", "utterance_type": "STATEMENT", "position": "0-60", "subject": {"label": "I", "type": []}, "predicate": {"label": "had heard about", "type": []}, "object": {"label": "utrecht", "type": []}, "perspective": {}, "context_id": null, "date": "2022-02-19T01:18:03.980054", "place": "", "place_id": null, "country": "", "region": "", "city": "", "objects": [], "people": []}, {"chat": 10, "turn": 79, "author": "Leolani", "utterance": "I did not know that! I had never heard about utrecht before!", "utterance_type": "STATEMENT", "position": "0-60", "subject": {"label": "I", "type": []}, "predicate": {"label": "had heard before about", "type": []}, "object": {"label": "utrecht", "type": []}, "perspective": {}, "context_id": null, "date": "2022-02-19T01:18:03.980054", "place": "", "place_id": null, "country": "", "region": "", "city": "", "objects": [], "people": []}, {"chat": 10, "turn": 80, "author": "Leolani", "utterance": "Utrecht is a city in The Netherlands", "utterance_type": "STATEMENT", "position": "0-36", "subject": {"label": "city", "type": []}, "predicate": {"label": "is in", "type": []}, "object": {"label": "Netherlands", "type": []}, "perspective": {}, "context_id": null, "date": "2022-02-19T01:18:10.516067", "place": "", "place_id": null, "country": "", "region": "", "city": "", "objects": [], "people": []}, {"chat": 10, "turn": 80, "author": "Leolani", "utterance": "Utrecht is a city in The Netherlands", "utterance_type": "STATEMENT", "position": "0-36", "subject": {"label": "Utrecht", "type": []}, "predicate": {"label": "is", "type": []}, "object": {"label": "city", "type": []}, "perspective": {}, "context_id": null, "date": "2022-02-19T01:18:10.516067", "place": "", "place_id": null, "country": "", "region": "", "city": "", "objects": [], "people": []}, {"chat": 10, "turn": 80, "author": "Leolani", "utterance": "Utrecht is a city in The Netherlands", "utterance_type": "STATEMENT", "position": "0-36", "subject": {"label": "Utrecht", "type": []}, "predicate": {"label": "is city in", "type": []}, "object": {"label": "Netherlands", "type": []}, "perspective": {}, "context_id": null, "date": "2022-02-19T01:18:10.516067", "place": "", "place_id": null, "country": "", "region": "", "city": "", "objects": [], "people": []}, {"chat": 10, "turn": 81, "author": "Leolani", "utterance": "Let me ask you something. What types of Instance like a city in tae netherlands do location orInstance usually be", "utterance_type": "STATEMENT", "position": "0-113", "subject": {"label": "city", "type": []}, "predicate": {"label": "is in", "type": []}, "object": {"label": "tae netherlands", "type": []}, "perspective": {}, "context_id": null, "date": "2022-02-19T01:18:17.018245", "place": "", "place_id": null, "country": "", "region": "", "city": "", "objects": [], "people": []}, {"chat": 10, "turn": 81, "author": "Leolani", "utterance": "Let me ask you something. What types of Instance like a city in tae netherlands do location orInstance usually be", "utterance_type": "STATEMENT", "position": "0-113", "subject": {"label": "me", "type": []}, "predicate": {"label": "ask", "type": []}, "object": {"label": "you", "type": []}, "perspective": {}, "context_id": null, "date": "2022-02-19T01:18:17.018245", "place": "", "place_id": null, "country": "", "region": "", "city": "", "objects": [], "people": []}, {"chat": 10, "turn": 81, "author": "Leolani", "utterance": "Let me ask you something. What types of Instance like a city in tae netherlands do location orInstance usually be", "utterance_type": "STATEMENT", "position": "0-113", "subject": {"label": "me", "type": []}, "predicate": {"label": "ask", "type": []}, "object": {"label": "something", "type": []}, "perspective": {}, "context_id": null, "date": "2022-02-19T01:18:17.018245", "place": "", "place_id": null, "country": "", "region": "", "city": "", "objects": [], "people": []}, {"chat": 10, "turn": 82, "author": "Leolani", "utterance": "Utrecht is a city in Holland", "utterance_type": "STATEMENT", "position": "0-28", "subject": {"label": "Utrecht", "type": []}, "predicate": {"label": "is city in", "type": []}, "object": {"label": "Holland", "type": []}, "perspective": {}, "context_id": null, "date": "2022-02-19T01:18:23.632029", "place": "", "place_id": null, "country": "", "region": "", "city": "", "objects": [], "people": []}, {"chat": 10, "turn": 82, "author": "Leolani", "utterance": "Utrecht is a city in Holland", "utterance_type": "STATEMENT", "position": "0-28", "subject": {"label": "Utrecht", "type": []}, "predicate": {"label": "is", "type": []}, "object": {"label": "city", "type": []}, "perspective": {}, "context_id": null, "date": "2022-02-19T01:18:23.632029", "place": "", "place_id": null, "country": "", "region": "", "city": "", "objects": [], "people": []}, {"chat": 10, "turn": 82, "author": "Leolani", "utterance": "Utrecht is a city in Holland", "utterance_type": "STATEMENT", "position": "0-28", "subject": {"label": "city", "type": []}, "predicate": {"label": "is in", "type": []}, "object": {"label": "Holland", "type": []}, "perspective": {}, "context_id": null, "date": "2022-02-19T01:18:23.632029", "place": "", "place_id": null, "country": "", "region": "", "city": "", "objects": [], "people": []}, {"chat": 10, "turn": 88, "author": "Leolani", "utterance": "Caya lives in Amsterdam", "utterance_type": "STATEMENT", "position": "0-23", "subject": {"label": "Caya", "type": []}, "predicate": {"label": "lives in", "type": []}, "object": {"label": "Amsterdam", "type": []}, "perspective": {}, "context_id": null, "date": "2022-02-19T01:19:02.637974", "place": "", "place_id": null, "country": "", "region": "", "city": "", "objects": [], "people": []}, {"chat": 10, "turn": 89, "author": "Leolani", "utterance": "Interesting! I had never heard about caya before!", "utterance_type": "STATEMENT", "position": "0-49", "subject": {"label": "I", "type": []}, "predicate": {"label": "had heard about", "type": []}, "object": {"label": "caya", "type": []}, "perspective": {}, "context_id": null, "date": "2022-02-19T01:19:09.145664", "place": "", "place_id": null, "country": "", "region": "", "city": "", "objects": [], "people": []}, {"chat": 10, "turn": 89, "author": "Leolani", "utterance": "Interesting! I had never heard about caya before!", "utterance_type": "STATEMENT", "position": "0-49", "subject": {"label": "I", "type": []}, "predicate": {"label": "had heard before about", "type": []}, "object": {"label": "caya", "type": []}, "perspective": {}, "context_id": null, "date": "2022-02-19T01:19:09.145664", "place": "", "place_id": null, "country": "", "region": "", "city": "", "objects": [], "people": []}, {"chat": 10, "turn": 95, "author": "Leolani", "utterance": "Caya told me ella like books", "utterance_type": "STATEMENT", "position": "0-28", "subject": {"label": "Caya", "type": []}, "predicate": {"label": "told", "type": []}, "object": {"label": "ella like books", "type": []}, "perspective": {}, "context_id": null, "date": "2022-02-19T01:19:48.094677", "place": "", "place_id": null, "country": "", "region": "", "city": "", "objects": [], "people": []}, {"chat": 10, "turn": 95, "author": "Leolani", "utterance": "Caya told me ella like books", "utterance_type": "STATEMENT", "position": "0-28", "subject": {"label": "Caya", "type": []}, "predicate": {"label": "told", "type": []}, "object": {"label": "ella", "type": []}, "perspective": {}, "context_id": null, "date": "2022-02-19T01:19:48.094677", "place": "", "place_id": null, "country": "", "region": "", "city": "", "objects": [], "people": []}, {"chat": 10, "turn": 95, "author": "Leolani", "utterance": "Caya told me ella like books", "utterance_type": "STATEMENT", "position": "0-28", "subject": {"label": "Caya", "type": []}, "predicate": {"label": "told", "type": []}, "object": {"label": "me", "type": []}, "perspective": {}, "context_id": null, "date": "2022-02-19T01:19:48.094677", "place": "", "place_id": null, "country": "", "region": "", "city": "", "objects": [], "people": []}, {"chat": 10, "turn": 99, "author": "Leolani", "utterance": "Caya told me caya own no object and that caya own a laptop ", "utterance_type": "STATEMENT", "position": "0-59", "subject": {"label": "Caya", "type": []}, "predicate": {"label": "told", "type": []}, "object": {"label": "me", "type": []}, "perspective": {}, "context_id": null, "date": "2022-02-19T01:20:13.839783", "place": "", "place_id": null, "country": "", "region": "", "city": "", "objects": [], "people": []}, {"chat": 10, "turn": 100, "author": "Leolani", "utterance": "A laptop is an object", "utterance_type": "STATEMENT", "position": "0-21", "subject": {"label": "laptop", "type": []}, "predicate": {"label": "is", "type": []}, "object": {"label": "object", "type": []}, "perspective": {}, "context_id": null, "date": "2022-02-19T01:20:20.441418", "place": "", "place_id": null, "country": "", "region": "", "city": "", "objects": [], "people": []}, {"chat": 10, "turn": 102, "author": "Leolani", "utterance": "Do you have any gossip?", "utterance_type": "STATEMENT", "position": "0-23", "subject": {"label": "you", "type": []}, "predicate": {"label": "Do have", "type": []}, "object": {"label": "gossip", "type": []}, "perspective": {}, "context_id": null, "date": "2022-02-19T01:20:33.351644", "place": "", "place_id": null, "country": "", "region": "", "city": "", "objects": [], "people": []}, {"chat": 10, "turn": 103, "author": "Leolani", "utterance": "I know agent usually do noun.communication, but I do not know this case", "utterance_type": "STATEMENT", "position": "0-71", "subject": {"label": "agent", "type": []}, "predicate": {"label": "usually do", "type": []}, "object": {"label": "noun.communication", "type": []}, "perspective": {}, "context_id": null, "date": "2022-02-19T01:20:39.752675", "place": "", "place_id": null, "country": "", "region": "", "city": "", "objects": [], "people": []}, {"chat": 10, "turn": 103, "author": "Leolani", "utterance": "I know agent usually do noun.communication, but I do not know this case", "utterance_type": "STATEMENT", "position": "0-71", "subject": {"label": "agent", "type": []}, "predicate": {"label": "do", "type": []}, "object": {"label": "noun.communication", "type": []}, "perspective": {}, "context_id": null, "date": "2022-02-19T01:20:39.752675", "place": "", "place_id": null, "country": "", "region": "", "city": "", "objects": [], "people": []}, {"chat": 10, "turn": 105, "author": "Leolani", "utterance": "I know noun.animal usually do noun.event, but I do not know this case", "utterance_type": "STATEMENT", "position": "0-69", "subject": {"label": "I", "type": []}, "predicate": {"label": "know", "type": []}, "object": {"label": "noun.animal", "type": []}, "perspective": {}, "context_id": null, "date": "2022-02-19T01:20:52.729583", "place": "", "place_id": null, "country": "", "region": "", "city": "", "objects": [], "people": []}, {"chat": 10, "turn": 106, "author": "Leolani", "utterance": "Mincke likes skiing", "utterance_type": "STATEMENT", "position": "0-19", "subject": {"label": "Mincke", "type": []}, "predicate": {"label": "likes", "type": []}, "object": {"label": "skiing", "type": []}, "perspective": {}, "context_id": null, "date": "2022-02-19T01:20:59.265523", "place": "", "place_id": null, "country": "", "region": "", "city": "", "objects": [], "people": []}, {"chat": 10, "turn": 109, "author": "Leolani", "utterance": "I am glad to have learned something new. I did not know anybody who like ski", "utterance_type": "STATEMENT", "position": "0-76", "subject": {"label": "I", "type": []}, "predicate": {"label": "learned", "type": []}, "object": {"label": "something new", "type": []}, "perspective": {}, "context_id": null, "date": "2022-02-19T01:21:18.756239", "place": "", "place_id": null, "country": "", "region": "", "city": "", "objects": [], "people": []}, {"chat": 10, "turn": 109, "author": "Leolani", "utterance": "I am glad to have learned something new. I did not know anybody who like ski", "utterance_type": "STATEMENT", "position": "0-76", "subject": {"label": "I", "type": []}, "predicate": {"label": "am", "type": []}, "object": {"label": "glad", "type": []}, "perspective": {}, "context_id": null, "date": "2022-02-19T01:21:18.756239", "place": "", "place_id": null, "country": "", "region": "", "city": "", "objects": [], "people": []}, {"chat": 10, "turn": 109, "author": "Leolani", "utterance": "I am glad to have learned something new. I did not know anybody who like ski", "utterance_type": "STATEMENT", "position": "0-76", "subject": {"label": "I", "type": []}, "predicate": {"label": "learned", "type": []}, "object": {"label": "something", "type": []}, "perspective": {}, "context_id": null, "date": "2022-02-19T01:21:18.756239", "place": "", "place_id": null, "country": "", "region": "", "city": "", "objects": [], "people": []}]